3_SYN/5_SYN/2_TINY_PROJECT/_4_BIT_SHIFT_REGISTER.v
`timescale 1ns / 1ps

module _4_BIT_SHIFT_REGISTER (
	// port list
	clr_n		, // active low(negative) reset
	clk		, // clock signal
	i_s		, // 2-bit mode select input (S1, S0)
	i_d		, // 4-bit parallel data input
	i_sr		, // 1-bit shift right serial input
	i_sl		, // 1-bit shift left serial input
	o_q		  // 4-bit data output
); 

// port declaration and IO direction
input 		clr_n		;
input 		clk		;
input 	[1:0] 	i_s		; 
input 	[3:0] 	i_d		; 
input 		i_sr		;
input 		i_sl		;
output 	[3:0] 	o_q		;

// type overriding
reg 	[3:0] 	o_q		;

// local parameters for FSM states
localparam S_HOLD = 2'b00	; // Hold data
localparam S_SHR  = 2'b01	; // Shift Right
localparam S_SHL  = 2'b10	; // Shift Left
localparam S_LOAD = 2'b11	; // Parallel Load

// FSM state registers: state (current) / next_state (combinational)
reg 	[1:0] 	state		;
reg 	[1:0] 	next_state	;

// datapath next-value evaluation variable
reg 	[3:0] 	next_q		;

// -----------------------------------------------------------------
// Process 1: FSM state register (sequential)
// Updates the current state on the rising edge of clk
// -----------------------------------------------------------------
always @(posedge clk or negedge clr_n)
begin
	if	( ~clr_n ) state	<= S_HOLD	; // active low | async reset to HOLD state
	else	state			<= next_state	; // move to the evaluated next state
end

// -----------------------------------------------------------------
// Process 2: next-state logic (combinational)
// Directly maps the mode select input i_s to the next state
// -----------------------------------------------------------------
always @(*)
begin
	next_state = i_s; // mode select input determines the next state
end

// -----------------------------------------------------------------
// Process 3: datapath next-value logic (combinational, ASIC style)
// Determines next_q based on the current FSM state
// -----------------------------------------------------------------
always @(*) 
begin
	next_q = o_q; // default assignment (prevents unintended latch inference)
	case ( state )
		S_HOLD	: next_q = o_q			; // keep current value
		S_SHR	: next_q = {i_sr, o_q[3:1]}	; // load i_sr into MSB, shift right
		S_SHL	: next_q = {o_q[2:0], i_sl}	; // load i_sl into LSB, shift left
		S_LOAD	: next_q = i_d			; // load 4-bit parallel data
		default	: next_q = o_q			; // keep current value on exception
	endcase
end

// -----------------------------------------------------------------
// Process 4: datapath register (sequential)
// Latches the evaluated next_q into o_q on the rising edge of clk
// -----------------------------------------------------------------
always @(posedge clk or negedge clr_n) 
begin
	if	( ~clr_n ) o_q	<= 4'b0000		; // active low | async reset to 0000
	else	o_q		<= next_q		; // update o_q with next_q on clock edge
end
	
endmodule

1_RTL/2_TINY_PROJECT/4_BIT_SHIFT_REGISTER/tb_4_BIT_SHIFT_REGISTER.v
`timescale 1ns / 1ps

module tb_4_BIT_SHIFT_REGISTER;

// stimulus signal
reg             clk             ;
reg             clr_n           ;
reg     [1:0]   i_s             ;
reg     [3:0]   i_d             ;
reg             i_sr            ;
reg             i_sl            ;

// monitor signal
wire    [3:0]   o_q             ;

// DUT instantiation
_4_BIT_SHIFT_REGISTER uut(
        .clr_n  (clr_n  )       ,
        .clk    (clk    )       ,
        .i_s    (i_s    )       ,
        .i_d    (i_d    )       ,
        .i_sr   (i_sr   )       ,
        .i_sl   (i_sl   )       ,
        .o_q    (o_q    )
);

// dumpfile gen
initial begin
        $dumpfile("./_4_BIT_SHIFT_REGISTER.vcd")         ;
        $dumpvars(0, tb_4_BIT_SHIFT_REGISTER)        ;
end

// clock generation
always #5 clk = ~clk;

// apply stimulus
initial begin
        // monitoring
        // NOTE: uut.state is added to the monitor because this DUT has a
        // real FSM state register. Since "state" is registered from i_s
        // (1-cycle delay) and o_q is registered from "state" (1 more
        // cycle delay), o_q always reflects i_s from TWO clock edges ago.
        // Watching uut.state alongside i_s/o_q makes this pipeline
        // behavior visible and lets you confirm the FSM is really
        // driven by a stored state, not by i_s directly.
        $monitor("Time=%0t | clk=%b | clr_n=%b | i_s=%b | state=%b | i_d=%b | i_sr=%b | i_sl=%b | o_q=%b",
                $time, clk, clr_n, i_s, uut.state, i_d, i_sr, i_sl, o_q);
	// init
        clk             = 1'b0          ;
        clr_n           = 1'b0          ;
        i_s             = 2'b00         ;
        i_d             = 4'b0000       ;
        i_sr            = 1'b0          ;
        i_sl            = 1'b0          ;
	// release async reset
        #12 clr_n       = 1'b1          ;
        
	// ---------------------------------------------------------
        // S_LOAD: parallel-load 4'b1010
        // Held for 2 cycles: 1 cycle for i_s to settle into "state",
        // 1 more cycle for that state to actually load into o_q.
	// ---------------------------------------------------------
        #10 i_s         = 2'b11         ; i_d  = 4'b1010 ;
        #10 ;   // settle cycle: state is now catching up to S_LOAD
        #10 ;   // o_q should now show the loaded value 4'b1010
        
	// ---------------------------------------------------------
        // S_HOLD: verify o_q stays unchanged
        // ---------------------------------------------------------
        #10 i_s         = 2'b00         ;
        #10 ;   // extra hold cycle to confirm o_q does not change

        // ---------------------------------------------------------
        // S_SHR: shift right, feeding i_sr = 1,0,1,0 in sequence
        // i_s is held at 2'b01 across this whole block so that once
        // "state" settles to S_SHR, every following clock edge
        // performs one real shift using the i_sr value present at
        // that edge.
        // ---------------------------------------------------------
        #10 i_s         = 2'b01         ; i_sr = 1'b1   ; // state settling to S_SHR
        #10 i_sr        = 1'b0          ;                 // first real shift happens here (uses i_sr=1)
        #10 i_sr        = 1'b1          ;                 // second real shift (uses i_sr=0)
        #10 i_sr        = 1'b0          ;                 // third real shift (uses i_sr=1)
        #10 ;                                              // fourth real shift (uses i_sr=0)

        // ---------------------------------------------------------
        // S_SHL: shift left, feeding i_sl = 1,0,1 in sequence
        // Same settle-then-shift pattern as S_SHR above.
        // ---------------------------------------------------------
        #10 i_s         = 2'b10         ; i_sl = 1'b1   ; // state settling to S_SHL
        #10 i_sl        = 1'b0          ;                 // first real shift (uses i_sl=1)
        #10 i_sl        = 1'b1          ;                 // second real shift (uses i_sl=0)
        #10 ;                                              // third real shift (uses i_sl=1)

        // ---------------------------------------------------------
        // S_HOLD: return to hold and confirm final value is stable
        // ---------------------------------------------------------
        #10 i_s         = 2'b00         ;
        #10 ;

        #20 $finish                     ;
end

endmodule

1_RTL/2_TINY_PROJECT/4_BIT_SHIFT_REGISTER/_4_BIT_SHIFT_REGISTER.vcd
$date
    Aug 18, 2026  09:03:20
$end
$version
    TOOL:	xmsim(64)	22.03-s012
$end
$timescale
    1 ps
$end

$scope module tb_4_BIT_SHIFT_REGISTER $end
$var reg       1 !    clk $end
$var reg       1 "    clr_n $end
$var reg       2 #    i_s [1:0] $end
$var reg       4 $    i_d [3:0] $end
$var reg       1 %    i_sr $end
$var reg       1 &    i_sl $end
$var wire      4 '    o_q [3:0] $end

$scope module uut $end
$var wire      1 (    clr_n  $end
$var wire      1 )    clk  $end
$var wire      2 *    i_s [1:0] $end
$var wire      4 +    i_d [3:0] $end
$var wire      1 ,    i_sr  $end
$var wire      1 -    i_sl  $end
$var reg       4 .    o_q [3:0] $end
$var parameter  2 /    S_HOLD $end
$var parameter  2 0    S_SHR $end
$var parameter  2 1    S_SHL $end
$var parameter  2 2    S_LOAD $end
$var reg       2 3    state [1:0] $end
$var reg       2 4    next_state [1:0] $end
$var reg       4 5    next_q [3:0] $end
$upscope $end

$upscope $end

$enddefinitions $end
$dumpvars
b11 2
b10 1
b1 0
b0 /
0!
0"
b0 #
b0 $
0%
0&
b0 '
0(
0)
b0 *
b0 +
0,
0-
b0 .
b0 3
b0 4
b0 5
$end
#5000
1!
1)
#10000
0!
0)
#12000
1"
1(
#15000
1!
1)
#20000
0!
0)
#22000
b11 #
b1010 $
b1010 +
b11 *
b11 4
#25000
1!
1)
b11 3
b1010 5
#30000
0!
0)
#35000
1!
1)
b1010 .
b1010 '
#40000
0!
0)
#45000
1!
1)
#50000
0!
0)
#52000
b0 #
b0 *
b0 4
#55000
1!
1)
b0 3
#60000
0!
0)
#65000
1!
1)
#70000
0!
0)
#72000
b1 #
1%
1,
b1 *
b1 4
#75000
1!
1)
b1 3
b1101 5
#80000
0!
0)
#82000
0%
0,
b1010 5
b101 5
#85000
1!
1)
b101 .
b10 5
b101 '
#90000
0!
0)
#92000
1%
1,
b101 5
b1010 5
#95000
1!
1)
b1010 .
b1101 5
b1010 '
#100000
0!
0)
#102000
0%
0,
b1010 5
b101 5
#105000
1!
1)
b101 .
b10 5
b101 '
#110000
0!
0)
#115000
1!
1)
b10 .
b1 5
b10 '
#120000
0!
0)
#122000
b10 #
1&
1-
b10 *
b10 5
b1 5
b10 4
#125000
1!
1)
b1 .
b10 3
b11 5
b1 '
#130000
0!
0)
#132000
0&
0-
b1 5
b10 5
#135000
1!
1)
b10 .
b100 5
b10 '
#140000
0!
0)
#142000
1&
1-
b10 5
b101 5
#145000
1!
1)
b101 .
b1011 5
b101 '
#150000
0!
0)
#155000
1!
1)
b1011 .
b111 5
b1011 '
#160000
0!
0)
#162000
b0 #
b0 *
b0 4
#165000
1!
1)
b111 .
b0 3
b111 '
